c2utils/__init__.py
c2utils/config/__init__.py
c2utils/config/config.py
c2utils/config/langconv.py
c2utils/config/pinyin_list.py
c2utils/config/zh_wiki.py
c2utils/config/vocabulary/baidu_stopwords.txt
c2utils/config/vocabulary/stopwords.txt
c2utils/config/vocabulary/user_dict.txt
c2utils/utils/__init__.py
c2utils/utils/calculation.py
c2utils/utils/common.py
c2utils/utils/data_processing.py
c2utils/utils/file_processing.py
c2utils/utils/text_processing.py
c2utils/utils/text_segmentation.py
c2utils/utils/time_processing.py
test/__init__.py
test/test_demo.py
c2utils-0.1.2.dist-info/LICENCE
c2utils-0.1.2.dist-info/METADATA
c2utils-0.1.2.dist-info/WHEEL
c2utils-0.1.2.dist-info/top_level.txt
c2utils-0.1.2.dist-info/RECORD
