Metadata-Version: 2.1
Name: c2utils
Version: 0.1.2
Summary: ChinaCreator Python Toolkit
Home-page: 
Author: Data Analysis Room
Author-email: 179965771@qq.com
Classifier: Programming Language :: Python :: 3
Classifier: License :: OSI Approved :: MIT License
Classifier: Operating System :: OS Independent
Requires-Python: >=3
License-File: LICENCE
Requires-Dist: jieba
Requires-Dist: pypinyin
Requires-Dist: pandas
